rate_limiter/__init__.py
rate_limiter/constants.py
rate_limiter/sentry_helper.py
rate_limiter/utils.py
sentry_rate_limiter-1.0.6.dist-info/METADATA
sentry_rate_limiter-1.0.6.dist-info/WHEEL
sentry_rate_limiter-1.0.6.dist-info/top_level.txt
sentry_rate_limiter-1.0.6.dist-info/RECORD
