Metadata-Version: 2.4
Name: sentry-rate-limiter
Version: 1.0.6
Summary: Add your description here
Requires-Python: >=3.12
Requires-Dist: kombu>=5.5.3
Provides-Extra: extra
Requires-Dist: requests>=2.32.3; extra == "extra"
Requires-Dist: sentry-sdk>=2.8.0; extra == "extra"
